{
  "colorScheme" : {
    "_colorLeft" : {"r":0.78431374,"g":0.07843138,"b":0.07843138},
    "_colorRight" : {"r":0.15686274,"g":0.55686271,"b":0.82352942},
    "_envColorLeft" : {"r":0.85000002,"g":0.08499997,"b":0.08499997},
    "_envColorRight" : {"r":0.18823528,"g":0.67529404,"b":1},
    "_obstacleColor" : {"r":1,"g":0.18823531,"b":0.18823531},
    "_envColorLeftBoost" : {"r":0,"g":0,"b":0},
    "_envColorRightBoost" : {"r":0,"g":0,"b":0}
  },
  "props" : {
    "0" : [
      {"_type":0,"_propId":3,"_lightId":3,"name":"DoubleColorLaser (9)","position":{"x":-3,"y":-1,"z":23}},
      {"_type":0,"_propId":3,"_lightId":8,"name":"DoubleColorLaser (8)","position":{"x":3,"y":-1,"z":23}},
      {"_type":0,"_propId":2,"_lightId":2,"name":"DoubleColorLaser (6)","position":{"x":3,"y":-1,"z":33}},
      {"_type":0,"_propId":2,"_lightId":5,"name":"DoubleColorLaser (7)","position":{"x":-3,"y":-1,"z":33}},
      {"_type":0,"_propId":4,"_lightId":4,"name":"DoubleColorLaser (4)","position":{"x":3,"y":-1,"z":43}},
      {"_type":0,"_propId":4,"_lightId":7,"name":"DoubleColorLaser (5)","position":{"x":-3,"y":-1,"z":43}},
      {"_type":0,"_propId":1,"_lightId":1,"name":"DoubleColorLaser (3)","position":{"x":-3,"y":-1,"z":53}},
      {"_type":0,"_propId":1,"_lightId":6,"name":"DoubleColorLaser (2)","position":{"x":3,"y":-1,"z":53}},
      {"_type":0,"_propId":0,"_lightId":0,"name":"DoubleColorLaser (1)","position":{"x":-3,"y":-1,"z":63}},
      {"_type":0,"_propId":0,"_lightId":12,"name":"DoubleColorLaser","position":{"x":3,"y":-1,"z":63}}
    ],
    "1" : [
      {"_type":1,"_propId":0,"_lightId":4,"name":"NeonTubeBothSidesDirectional","position":{"x":20.651,"y":15.463,"z":7}},
      {"_type":1,"_propId":0,"_lightId":5,"name":"NeonTubeBothSidesDirectional (1)","position":{"x":-20.651,"y":-5.463,"z":7}},
      {"_type":1,"_propId":0,"_lightId":6,"name":"NeonTubeBothSidesDirectional (2)","position":{"x":10.463,"y":-15.651,"z":7}},
      {"_type":1,"_propId":0,"_lightId":7,"name":"NeonTubeBothSidesDirectional (3)","position":{"x":-10.463,"y":25.651,"z":7}},
      {"_type":1,"_propId":1,"_lightId":8,"name":"NeonTubeBothSidesDirectional","position":{"x":22.041,"y":12.079,"z":15}},
      {"_type":1,"_propId":1,"_lightId":9,"name":"NeonTubeBothSidesDirectional (1)","position":{"x":-22.041,"y":-2.079,"z":15}},
      {"_type":1,"_propId":1,"_lightId":10,"name":"NeonTubeBothSidesDirectional (2)","position":{"x":7.079,"y":-17.041,"z":15}},
      {"_type":1,"_propId":1,"_lightId":11,"name":"NeonTubeBothSidesDirectional (3)","position":{"x":-7.079,"y":27.041,"z":15}},
      {"_type":1,"_propId":2,"_lightId":12,"name":"NeonTubeBothSidesDirectional","position":{"x":23.15,"y":5,"z":23}},
      {"_type":1,"_propId":2,"_lightId":13,"name":"NeonTubeBothSidesDirectional (1)","position":{"x":-23.15,"y":5,"z":23}},
      {"_type":1,"_propId":2,"_lightId":14,"name":"NeonTubeBothSidesDirectional (2)","position":{"x":0,"y":-18.15,"z":23}},
      {"_type":1,"_propId":2,"_lightId":15,"name":"NeonTubeBothSidesDirectional (3)","position":{"x":0,"y":28.15,"z":23}},
      {"_type":1,"_propId":3,"_lightId":16,"name":"NeonTubeBothSidesDirectional","position":{"x":23.15,"y":5,"z":31}},
      {"_type":1,"_propId":3,"_lightId":17,"name":"NeonTubeBothSidesDirectional (1)","position":{"x":-23.15,"y":5,"z":31}},
      {"_type":1,"_propId":3,"_lightId":18,"name":"NeonTubeBothSidesDirectional (2)","position":{"x":0,"y":-18.15,"z":31}},
      {"_type":1,"_propId":3,"_lightId":19,"name":"NeonTubeBothSidesDirectional (3)","position":{"x":0,"y":28.15,"z":31}},
      {"_type":1,"_propId":4,"_lightId":20,"name":"NeonTubeBothSidesDirectional","position":{"x":23.15,"y":5,"z":39}},
      {"_type":1,"_propId":4,"_lightId":21,"name":"NeonTubeBothSidesDirectional (1)","position":{"x":-23.15,"y":5,"z":39}},
      {"_type":1,"_propId":4,"_lightId":22,"name":"NeonTubeBothSidesDirectional (2)","position":{"x":0,"y":-18.15,"z":39}},
      {"_type":1,"_propId":4,"_lightId":23,"name":"NeonTubeBothSidesDirectional (3)","position":{"x":0,"y":28.15,"z":39}},
      {"_type":1,"_propId":5,"_lightId":24,"name":"NeonTubeBothSidesDirectional","position":{"x":23.15,"y":5,"z":47}},
      {"_type":1,"_propId":5,"_lightId":25,"name":"NeonTubeBothSidesDirectional (1)","position":{"x":-23.15,"y":5,"z":47}},
      {"_type":1,"_propId":5,"_lightId":26,"name":"NeonTubeBothSidesDirectional (2)","position":{"x":0,"y":-18.15,"z":47}},
      {"_type":1,"_propId":5,"_lightId":27,"name":"NeonTubeBothSidesDirectional (3)","position":{"x":0,"y":28.15,"z":47}},
      {"_type":1,"_propId":6,"_lightId":28,"name":"NeonTubeBothSidesDirectional","position":{"x":23.15,"y":5,"z":55}},
      {"_type":1,"_propId":6,"_lightId":29,"name":"NeonTubeBothSidesDirectional (1)","position":{"x":-23.15,"y":5,"z":55}},
      {"_type":1,"_propId":6,"_lightId":30,"name":"NeonTubeBothSidesDirectional (2)","position":{"x":0,"y":-18.15,"z":55}},
      {"_type":1,"_propId":6,"_lightId":31,"name":"NeonTubeBothSidesDirectional (3)","position":{"x":0,"y":28.15,"z":55}},
      {"_type":1,"_propId":7,"_lightId":32,"name":"NeonTubeBothSidesDirectional","position":{"x":23.15,"y":5,"z":63}},
      {"_type":1,"_propId":7,"_lightId":33,"name":"NeonTubeBothSidesDirectional (1)","position":{"x":-23.15,"y":5,"z":63}},
      {"_type":1,"_propId":7,"_lightId":34,"name":"NeonTubeBothSidesDirectional (2)","position":{"x":0,"y":-18.15,"z":63}},
      {"_type":1,"_propId":7,"_lightId":35,"name":"NeonTubeBothSidesDirectional (3)","position":{"x":0,"y":28.15,"z":63}},
      {"_type":1,"_propId":8,"_lightId":36,"name":"NeonTubeBothSidesDirectional","position":{"x":23.15,"y":5,"z":71}},
      {"_type":1,"_propId":8,"_lightId":37,"name":"NeonTubeBothSidesDirectional (1)","position":{"x":-23.15,"y":5,"z":71}},
      {"_type":1,"_propId":8,"_lightId":38,"name":"NeonTubeBothSidesDirectional (2)","position":{"x":0,"y":-18.15,"z":71}},
      {"_type":1,"_propId":8,"_lightId":39,"name":"NeonTubeBothSidesDirectional (3)","position":{"x":0,"y":28.15,"z":71}},
      {"_type":1,"_propId":9,"_lightId":40,"name":"NeonTubeBothSidesDirectional","position":{"x":23.15,"y":5,"z":79}},
      {"_type":1,"_propId":9,"_lightId":41,"name":"NeonTubeBothSidesDirectional (1)","position":{"x":-23.15,"y":5,"z":79}},
      {"_type":1,"_propId":9,"_lightId":42,"name":"NeonTubeBothSidesDirectional (2)","position":{"x":0,"y":-18.15,"z":79}},
      {"_type":1,"_propId":9,"_lightId":43,"name":"NeonTubeBothSidesDirectional (3)","position":{"x":0,"y":28.15,"z":79}},
      {"_type":1,"_propId":10,"_lightId":44,"name":"NeonTubeBothSidesDirectional","position":{"x":23.15,"y":5,"z":87}},
      {"_type":1,"_propId":10,"_lightId":45,"name":"NeonTubeBothSidesDirectional (1)","position":{"x":-23.15,"y":5,"z":87}},
      {"_type":1,"_propId":10,"_lightId":46,"name":"NeonTubeBothSidesDirectional (2)","position":{"x":0,"y":-18.15,"z":87}},
      {"_type":1,"_propId":10,"_lightId":47,"name":"NeonTubeBothSidesDirectional (3)","position":{"x":0,"y":28.15,"z":87}},
      {"_type":1,"_propId":11,"_lightId":48,"name":"NeonTubeBothSidesDirectional","position":{"x":23.15,"y":5,"z":95}},
      {"_type":1,"_propId":11,"_lightId":49,"name":"NeonTubeBothSidesDirectional (1)","position":{"x":-23.15,"y":5,"z":95}},
      {"_type":1,"_propId":11,"_lightId":50,"name":"NeonTubeBothSidesDirectional (2)","position":{"x":0,"y":-18.15,"z":95}},
      {"_type":1,"_propId":11,"_lightId":51,"name":"NeonTubeBothSidesDirectional (3)","position":{"x":0,"y":28.15,"z":95}},
      {"_type":1,"_propId":12,"_lightId":52,"name":"NeonTubeBothSidesDirectional","position":{"x":23.15,"y":5,"z":103}},
      {"_type":1,"_propId":12,"_lightId":53,"name":"NeonTubeBothSidesDirectional (1)","position":{"x":-23.15,"y":5,"z":103}},
      {"_type":1,"_propId":12,"_lightId":54,"name":"NeonTubeBothSidesDirectional (2)","position":{"x":0,"y":-18.15,"z":103}},
      {"_type":1,"_propId":12,"_lightId":55,"name":"NeonTubeBothSidesDirectional (3)","position":{"x":0,"y":28.15,"z":103}},
      {"_type":1,"_propId":13,"_lightId":56,"name":"NeonTubeBothSidesDirectional","position":{"x":23.15,"y":5,"z":111}},
      {"_type":1,"_propId":13,"_lightId":57,"name":"NeonTubeBothSidesDirectional (1)","position":{"x":-23.15,"y":5,"z":111}},
      {"_type":1,"_propId":13,"_lightId":58,"name":"NeonTubeBothSidesDirectional (2)","position":{"x":0,"y":-18.15,"z":111}},
      {"_type":1,"_propId":13,"_lightId":59,"name":"NeonTubeBothSidesDirectional (3)","position":{"x":0,"y":28.15,"z":111}},
      {"_type":1,"_propId":14,"_lightId":60,"name":"NeonTubeBothSidesDirectional","position":{"x":23.15,"y":5,"z":119}},
      {"_type":1,"_propId":14,"_lightId":61,"name":"NeonTubeBothSidesDirectional (1)","position":{"x":-23.15,"y":5,"z":119}},
      {"_type":1,"_propId":14,"_lightId":62,"name":"NeonTubeBothSidesDirectional (2)","position":{"x":0,"y":-18.15,"z":119}},
      {"_type":1,"_propId":14,"_lightId":63,"name":"NeonTubeBothSidesDirectional (3)","position":{"x":0,"y":28.15,"z":119}}
    ],
    "2" : [
      {"_type":2,"_propId":9,"_lightId":12,"name":"NeonTubeDirectionalL","position":{"x":-2.355,"y":0.02,"z":7.75}},
      {"_type":2,"_propId":7,"_lightId":9,"name":"NeonTubeDirectional (1)","position":{"x":-17.45,"y":-2.5,"z":15}},
      {"_type":2,"_propId":0,"_lightId":0,"name":"NeonTubeDirectional","position":{"x":-17.45,"y":0,"z":19}},
      {"_type":2,"_propId":0,"_lightId":13,"name":"NeonTube (2)","position":{"x":-20,"y":30,"z":19}},
      {"_type":2,"_propId":8,"_lightId":10,"name":"Laser","position":{"x":-25,"y":-5,"z":40}},
      {"_type":2,"_propId":2,"_lightId":3,"name":"Laser","position":{"x":-25,"y":-5,"z":41}},
      {"_type":2,"_propId":1,"_lightId":2,"name":"Laser","position":{"x":-25,"y":-5,"z":42}},
      {"_type":2,"_propId":5,"_lightId":6,"name":"Laser","position":{"x":-25,"y":-5,"z":43}},
      {"_type":2,"_propId":6,"_lightId":7,"name":"Laser","position":{"x":-25,"y":-5,"z":44}},
      {"_type":2,"_propId":3,"_lightId":4,"name":"Laser","position":{"x":-25,"y":-5,"z":45}},
      {"_type":2,"_propId":4,"_lightId":5,"name":"Laser","position":{"x":-25,"y":-5,"z":46}}
    ],
    "3" : [
      {"_type":3,"_propId":8,"_lightId":12,"name":"NeonTubeDirectionalR","position":{"x":2.355,"y":0.02,"z":7.75}},
      {"_type":3,"_propId":9,"_lightId":14,"name":"NeonTubeDirectional (1)","position":{"x":17.45,"y":-2.5,"z":15}},
      {"_type":3,"_propId":0,"_lightId":0,"name":"NeonTube (2)","position":{"x":20,"y":30,"z":19}},
      {"_type":3,"_propId":0,"_lightId":2,"name":"NeonTubeDirectional","position":{"x":17.45,"y":0,"z":19}},
      {"_type":3,"_propId":7,"_lightId":10,"name":"Laser","position":{"x":25,"y":-5,"z":40}},
      {"_type":3,"_propId":2,"_lightId":4,"name":"Laser","position":{"x":25,"y":-5,"z":41}},
      {"_type":3,"_propId":1,"_lightId":3,"name":"Laser","position":{"x":25,"y":-5,"z":42}},
      {"_type":3,"_propId":5,"_lightId":7,"name":"Laser","position":{"x":25,"y":-5,"z":43}},
      {"_type":3,"_propId":6,"_lightId":8,"name":"Laser","position":{"x":25,"y":-5,"z":44}},
      {"_type":3,"_propId":3,"_lightId":5,"name":"Laser","position":{"x":25,"y":-5,"z":45}},
      {"_type":3,"_propId":4,"_lightId":6,"name":"Laser","position":{"x":25,"y":-5,"z":46}}
    ],
    "4" : [
      {"_type":4,"_propId":6,"_lightId":14,"name":"BackColumnNeon","position":{"x":-3,"y":0.239,"z":-19.342}},
      {"_type":4,"_propId":6,"_lightId":16,"name":"BackColumnNeon","position":{"x":3,"y":0.239,"z":-19.342}},
      {"_type":4,"_propId":1,"_lightId":1,"name":"Feet","position":{"x":0,"y":0.005,"z":0}},
      {"_type":4,"_propId":1,"_lightId":2,"name":"RectangleFakeGlow","position":{"x":0,"y":0.01,"z":0}},
      {"_type":4,"_propId":3,"_lightId":6,"name":"DoubleColorLaser (9)","position":{"x":-3,"y":-1,"z":23}},
      {"_type":4,"_propId":3,"_lightId":10,"name":"DoubleColorLaser (8)","position":{"x":3,"y":-1,"z":23}},
      {"_type":4,"_propId":2,"_lightId":5,"name":"DoubleColorLaser (6)","position":{"x":3,"y":-1,"z":33}},
      {"_type":4,"_propId":2,"_lightId":13,"name":"DoubleColorLaser (7)","position":{"x":-3,"y":-1,"z":33}},
      {"_type":4,"_propId":5,"_lightId":9,"name":"DoubleColorLaser (5)","position":{"x":-3,"y":-1,"z":43}},
      {"_type":4,"_propId":5,"_lightId":12,"name":"DoubleColorLaser (4)","position":{"x":3,"y":-1,"z":43}},
      {"_type":4,"_propId":4,"_lightId":7,"name":"DoubleColorLaser (3)","position":{"x":-3,"y":-1,"z":53}},
      {"_type":4,"_propId":4,"_lightId":11,"name":"DoubleColorLaser (2)","position":{"x":3,"y":-1,"z":53}},
      {"_type":4,"_propId":0,"_lightId":0,"name":"DoubleColorLaser","position":{"x":3,"y":-1,"z":63}},
      {"_type":4,"_propId":0,"_lightId":8,"name":"DoubleColorLaser (1)","position":{"x":-3,"y":-1,"z":63}}
    ]
  }
}